{
  "type": "minecraft:crafting_shaped",
  "category": "misc",
  "pattern": [
    "  2",
    " 45",
    "678"
  ],
  "key": {
    "2": {
      "item": "genshin_core:fir_wood"
    },
    "4": {
      "item": "genshin_core:fir_wood"
    },
    "5": {
      "item": "genshin_core:fir_wood"
    },
    "6": {
      "item": "genshin_core:fir_wood"
    },
    "7": {
      "item": "genshin_core:fir_wood"
    },
    "8": {
      "item": "genshin_core:fir_wood"
    }
  },
  "result": {
    "item": "genshin_core:fir_wood_stairs",
    "count": 4
  }
}